msb/__init__.py
msb/server.py
msb/versioncheck.py
msb-0.4.dist-info/LICENSE
msb-0.4.dist-info/METADATA
msb-0.4.dist-info/WHEEL
msb-0.4.dist-info/top_level.txt
msb-0.4.dist-info/RECORD
