Metadata-Version: 2.1
Name: msb
Version: 0.4
Summary: Package for Minecraft Server Builder
Home-page: https://msb.gerotworld.ru
Author: nomfodm
Author-email: nomfodm@gmail.com
License: UNKNOWN
Project-URL: Bug Tracker, https://github.com/nomfodm/msb/issues
Platform: UNKNOWN
Classifier: Programming Language :: Python :: 3
Classifier: License :: OSI Approved :: MIT License
Classifier: Operating System :: OS Independent
Requires-Python: >=3.6
License-File: LICENSE
Requires-Dist: requests
Requires-Dist: tqdm
Requires-Dist: bs4
